virtuals_observer/__init__.py
virtuals_observer/cli.py
virtuals_observer/mcp_server.py
virtuals_observer/twitter_api.py
virtuals_tweepy_mcp-0.1.2.dist-info/METADATA
virtuals_tweepy_mcp-0.1.2.dist-info/WHEEL
virtuals_tweepy_mcp-0.1.2.dist-info/entry_points.txt
virtuals_tweepy_mcp-0.1.2.dist-info/RECORD
