Metadata-Version: 2.4
Name: virtuals-tweepy-mcp
Version: 0.1.2
Summary: MCP server for X (Twitter) via Virtuals GAME SDK - 37 tools for tweets, search, users, and engagement
Project-URL: Homepage, https://github.com/kyoungrok0517/virtuals-tweepy-mcp
Project-URL: Repository, https://github.com/kyoungrok0517/virtuals-tweepy-mcp
Project-URL: Issues, https://github.com/kyoungrok0517/virtuals-tweepy-mcp/issues
Author-email: Kyoungrok Jang <kyoungrok.jang@gmail.com>
License-Expression: MIT
Keywords: agent,ai,game-sdk,llm,mcp,twitter,virtuals,x
Classifier: Development Status :: 4 - Beta
Classifier: Intended Audience :: Developers
Classifier: License :: OSI Approved :: MIT License
Classifier: Programming Language :: Python :: 3
Classifier: Programming Language :: Python :: 3.12
Classifier: Topic :: Software Development :: Libraries :: Python Modules
Requires-Python: >=3.12
Requires-Dist: mcp>=1.0.0
Requires-Dist: playwright>=1.57.0
Requires-Dist: python-dotenv>=1.2.1
Requires-Dist: twitter-plugin-gamesdk>=0.2.11
Requires-Dist: virtuals-tweepy>=0.1.6
Provides-Extra: article
Requires-Dist: playwright>=1.40.0; extra == 'article'
